BundestagsAPy/__init__.py
BundestagsAPy/client.py
BundestagsAPy/errors.py
BundestagsAPy/models.py
BundestagsAPy/parsers.py
BundestagsAPy-1.2a0.dist-info/LICENSE
BundestagsAPy-1.2a0.dist-info/METADATA
BundestagsAPy-1.2a0.dist-info/WHEEL
BundestagsAPy-1.2a0.dist-info/top_level.txt
BundestagsAPy-1.2a0.dist-info/RECORD
