Metadata-Version: 2.1
Name: BundestagsAPy
Version: 1.2a0
Summary: Python Wrapper for the Bundestags API
Author: Paul Bose
Author-email: <bose@ese.eur.nl>
Keywords: Bundestag,API
Classifier: Development Status :: 3 - Alpha
Classifier: Intended Audience :: Education
Classifier: Programming Language :: Python :: 3.7
Classifier: Operating System :: MacOS :: MacOS X
Classifier: Operating System :: Microsoft :: Windows
License-File: LICENSE
Requires-Dist: requests (<3,>=2.26.0)
